README.md
setup.py
heurisp/__init__.py
heurisp/heurisp.py
heurisp.egg-info/PKG-INFO
heurisp.egg-info/SOURCES.txt
heurisp.egg-info/dependency_links.txt
heurisp.egg-info/requires.txt
heurisp.egg-info/top_level.txt
test/test.py