Metadata-Version: 2.1
Name: heurisp
Version: 0.3.0
Summary: Heuristics for Sampling-based Path Planner
Home-page: https://github.com/liespace/pyHSP
Author: Gabel Liemann
Author-email: troubleli233@gmail.com
License: MIT
Platform: UNKNOWN
Classifier: Programming Language :: Python :: 2
Classifier: License :: OSI Approved :: MIT License
Classifier: Operating System :: OS Independent
